graphqler/__init__.py
graphqler/__main__.py
graphqler/compiler/__init__.py
graphqler/compiler/compiler.py
graphqler/compiler/introspection_query.py
graphqler/compiler/parsers/__init__.py
graphqler/compiler/parsers/enum_list_parser.py
graphqler/compiler/parsers/input_object_list_parser.py
graphqler/compiler/parsers/interface_list_parser.py
graphqler/compiler/parsers/mutation_list_parser.py
graphqler/compiler/parsers/object_list_parser.py
graphqler/compiler/parsers/parser.py
graphqler/compiler/parsers/query_list_parser.py
graphqler/compiler/parsers/union_list_parser.py
graphqler/compiler/resolvers/__init__.py
graphqler/compiler/resolvers/mutation_object_resolver.py
graphqler/compiler/resolvers/object_dependency_resolver.py
graphqler/compiler/resolvers/object_method_resolver.py
graphqler/compiler/resolvers/query_object_resolver.py
graphqler/compiler/resolvers/resolver.py
graphqler/compiler/resolvers/utils.py
graphqler/config.py
graphqler/core.py
graphqler/fuzzer/__init__.py
graphqler/fuzzer/engine/dengine.py
graphqler/fuzzer/engine/detectors/__init__.py
graphqler/fuzzer/engine/detectors/detector.py
graphqler/fuzzer/engine/detectors/field_suggestion/field_suggestion_detector.py
graphqler/fuzzer/engine/detectors/field_suggestion/field_suggestion_materializer.py
graphqler/fuzzer/engine/detectors/html_injection/html_injection_detector.py
graphqler/fuzzer/engine/detectors/introspection/introspection_detector.py
graphqler/fuzzer/engine/detectors/introspection/introspection_materializer.py
graphqler/fuzzer/engine/detectors/os_command_injection/os_command_injection_detector.py
graphqler/fuzzer/engine/detectors/os_command_injection/os_command_injection_materializer.py
graphqler/fuzzer/engine/detectors/path_injection/path_injection_detector.py
graphqler/fuzzer/engine/detectors/query_deny_bypass/query_deny_bypass_detector.py
graphqler/fuzzer/engine/detectors/sql_injection/sql_injection_detector.py
graphqler/fuzzer/engine/detectors/ssrf_injection/ssrf_injection_detector.py
graphqler-2.3.6.dist-info/LICENSE
graphqler-2.3.6.dist-info/METADATA
graphqler-2.3.6.dist-info/WHEEL
graphqler-2.3.6.dist-info/RECORD
