Metadata-Version: 2.1
Name: GraphQLer
Version: 2.3.6
Summary: A cutting edge context aware GraphQL API fuzzing tool!
License: MIT
Author: Omar2535
Author-email: omar@9tsai.ca
Requires-Python: >=3.12,<3.13
Classifier: License :: OSI Approved :: MIT License
Classifier: Programming Language :: Python :: 3
Classifier: Programming Language :: Python :: 3.12
Requires-Dist: aiodns (==3.2.0)
Requires-Dist: aiohttp (==3.10.10)
Requires-Dist: aiosignal (==1.3.1)
Requires-Dist: astroid (==2.15.8)
Requires-Dist: asttokens (==2.4.0)
Requires-Dist: asyncio (==3.4.3)
Requires-Dist: attrs (==23.1.0)
Requires-Dist: backcall (==0.2.0)
Requires-Dist: backports-entry-points-selectable (==1.2.0)
Requires-Dist: black (==24.3.0)
Requires-Dist: brotli (==1.1.0)
Requires-Dist: certifi (==2024.7.4)
Requires-Dist: cffi (==1.16.0)
Requires-Dist: cfgv (==3.4.0)
Requires-Dist: charset-normalizer (==3.2.0)
Requires-Dist: clairvoyance (==2.5.2)
Requires-Dist: click (==8.1.7)
Requires-Dist: cloudpickle (>=3.1.0,<4.0.0)
Requires-Dist: colorama (==0.4.6)
Requires-Dist: colorclass (==2.2.2)
Requires-Dist: contourpy (==1.1.1)
Requires-Dist: coverage (==7.3.1)
Requires-Dist: cycler (==0.12.1)
Requires-Dist: decorator (==5.1.1)
Requires-Dist: dill (==0.3.7)
Requires-Dist: distlib (==0.3.7)
Requires-Dist: docopt (==0.6.2)
Requires-Dist: executing (==2.0.0)
Requires-Dist: filelock (==3.12.4)
Requires-Dist: fonttools (==4.43.1)
Requires-Dist: frozenlist (==1.4.1)
Requires-Dist: graphql-core (==3.2.5)
Requires-Dist: identify (==2.5.29)
Requires-Dist: idna (==3.7)
Requires-Dist: importlib-metadata (==6.8.0)
Requires-Dist: iniconfig (==2.0.0)
Requires-Dist: ipython (==8.16.1)
Requires-Dist: isort (==5.12.0)
Requires-Dist: jedi (==0.19.1)
Requires-Dist: jinja2 (==3.1.4)
Requires-Dist: jsonpickle (==3.0.2)
Requires-Dist: kiwisolver (==1.4.5)
Requires-Dist: lazy-object-proxy (==1.9.0)
Requires-Dist: levenshtein (==0.23.0)
Requires-Dist: markdown-it-py (==3.0.0)
Requires-Dist: markupsafe (==2.1.3)
Requires-Dist: matplotlib (==3.8.0)
Requires-Dist: matplotlib-inline (==0.1.6)
Requires-Dist: mccabe (==0.7.0)
Requires-Dist: mdurl (==0.1.2)
Requires-Dist: multidict (==6.0.5)
Requires-Dist: mypy-extensions (==1.0.0)
Requires-Dist: networkx (==3.1)
Requires-Dist: nodeenv (==1.8.0)
Requires-Dist: num2words (==0.5.12)
Requires-Dist: numpy (==1.26.0)
Requires-Dist: packaging (==23.1)
Requires-Dist: parso (==0.8.3)
Requires-Dist: pathspec (==0.11.2)
Requires-Dist: pexpect (==4.8.0)
Requires-Dist: pickleshare (==0.7.5)
Requires-Dist: pillow (==10.3.0)
Requires-Dist: pip-upgrader (==1.4.15)
Requires-Dist: platformdirs (==3.10.0)
Requires-Dist: pluggy (==1.3.0)
Requires-Dist: prompt-toolkit (==3.0.39)
Requires-Dist: ptyprocess (==0.7.0)
Requires-Dist: pure-eval (==0.2.2)
Requires-Dist: pycares (==4.4.0)
Requires-Dist: pycodestyle (==2.11.0)
Requires-Dist: pycparser (==2.22)
Requires-Dist: pyflakes (==3.1.0)
Requires-Dist: pygments (==2.16.1)
Requires-Dist: pylint (==2.17.6)
Requires-Dist: pyparsing (==3.1.1)
Requires-Dist: python-dateutil (==2.9.0)
Requires-Dist: python-levenshtein (==0.23.0)
Requires-Dist: pyyaml (==6.0.1)
Requires-Dist: rapidfuzz (==3.4.0)
Requires-Dist: requests (==2.32.3)
Requires-Dist: rich (==13.7.1)
Requires-Dist: scipy (>=1.14.1,<2.0.0)
Requires-Dist: setuptools (==70.0.0)
Requires-Dist: six (==1.16.0)
Requires-Dist: stack-data (==0.6.3)
Requires-Dist: terminaltables (==3.1.10)
Requires-Dist: tomli (==2.0.1)
Requires-Dist: tomlkit (==0.12.1)
Requires-Dist: traitlets (==5.11.2)
Requires-Dist: typed-ast (==1.5.5)
Requires-Dist: typing-extensions (==4.8.0)
Requires-Dist: urllib3 (==2.2.2)
Requires-Dist: virtualenv (==20.24.5)
Requires-Dist: wcwidth (==0.2.8)
Requires-Dist: wrapt (==1.15.0)
Requires-Dist: yarl (==1.16.0)
Requires-Dist: zipp (==3.19.1)
